blank_format/__init__.py
blank_format/main.py
blank_format-0.2.3.dist-info/entry_points.txt
blank_format-0.2.3.dist-info/WHEEL
blank_format-0.2.3.dist-info/METADATA
blank_format-0.2.3.dist-info/RECORD
